LICENSE.txt
setup.py
AFRITONPy1.egg-info/PKG-INFO
AFRITONPy1.egg-info/SOURCES.txt
AFRITONPy1.egg-info/dependency_links.txt
AFRITONPy1.egg-info/top_level.txt
name_afrit/AFRI.py
name_afrit/OS.py
name_afrit/S_X.py
name_afrit/Taiwn.py
name_afrit/__init__.py